{
    "slug": "linaje-salvaje",
    "nombre": "Linaje Salvaje",
    "municipio": "Calarcá",
    "ubicacion": "Vía Albania km 8 Vía Calarcá - Barcelona, Quindío",
    "contacto": {
        "telefono": "+57 313 732 1433",
        "whatsapp": "573137321433",
        "email": "",
        "web_oficial": ""
    },
    "descripcion": "Hotel en Calarcá, Quindío, con habitaciones, WiFi, desayuno y parqueadero.",
    "experiencias": [],
    "multimedia": {
        "fotos": [],
        "videos": []
    }
}